{
  "id": "0bf73925-926e-4262-921a-790cb14c045e",
  "prevId": "00000000-0000-0000-0000-000000000000",
  "version": "7",
  "dialect": "postgresql",
  "tables": {
    "public.alerts": {
      "name": "alerts",
      "schema": "",
      "columns": {
        "id": {
          "name": "id",
          "type": "uuid",
          "primaryKey": true,
          "notNull": true,
          "default": "gen_random_uuid()"
        },
        "meter_id": {
          "name": "meter_id",
          "type": "uuid",
          "primaryKey": false,
          "notNull": true
        },
        "alert_type": {
          "name": "alert_type",
          "type": "alert_type",
          "typeSchema": "public",
          "primaryKey": false,
          "notNull": true
        },
        "severity": {
          "name": "severity",
          "type": "severity",
          "typeSchema": "public",
          "primaryKey": false,
          "notNull": true,
          "default": "'info'"
        },
        "message": {
          "name": "message",
          "type": "text",
          "primaryKey": false,
          "notNull": false
        },
        "acknowledged": {
          "name": "acknowledged",
          "type": "boolean",
          "primaryKey": false,
          "notNull": true,
          "default": false
        },
        "created_at": {
          "name": "created_at",
          "type": "timestamp with time zone",
          "primaryKey": false,
          "notNull": true,
          "default": "now()"
        }
      },
      "indexes": {
        "idx_alerts_meter": {
          "name": "idx_alerts_meter",
          "columns": [
            {
              "expression": "meter_id",
              "isExpression": false,
              "asc": true,
              "nulls": "last"
            },
            {
              "expression": "created_at",
              "isExpression": false,
              "asc": false,
              "nulls": "last"
            }
          ],
          "isUnique": false,
          "concurrently": false,
          "method": "btree",
          "with": {}
        }
      },
      "foreignKeys": {
        "alerts_meter_id_meters_id_fk": {
          "name": "alerts_meter_id_meters_id_fk",
          "tableFrom": "alerts",
          "tableTo": "meters",
          "columnsFrom": [
            "meter_id"
          ],
          "columnsTo": [
            "id"
          ],
          "onDelete": "cascade",
          "onUpdate": "no action"
        }
      },
      "compositePrimaryKeys": {},
      "uniqueConstraints": {},
      "policies": {},
      "checkConstraints": {},
      "isRLSEnabled": false
    },
    "public.invoices": {
      "name": "invoices",
      "schema": "",
      "columns": {
        "id": {
          "name": "id",
          "type": "uuid",
          "primaryKey": true,
          "notNull": true,
          "default": "gen_random_uuid()"
        },
        "user_id": {
          "name": "user_id",
          "type": "uuid",
          "primaryKey": false,
          "notNull": true
        },
        "service_point_id": {
          "name": "service_point_id",
          "type": "uuid",
          "primaryKey": false,
          "notNull": true
        },
        "total_kwh": {
          "name": "total_kwh",
          "type": "numeric(12, 4)",
          "primaryKey": false,
          "notNull": true
        },
        "amount_due": {
          "name": "amount_due",
          "type": "numeric(12, 2)",
          "primaryKey": false,
          "notNull": true
        },
        "invoice_status": {
          "name": "invoice_status",
          "type": "invoice_status",
          "typeSchema": "public",
          "primaryKey": false,
          "notNull": true,
          "default": "'unpaid'"
        },
        "period_start": {
          "name": "period_start",
          "type": "date",
          "primaryKey": false,
          "notNull": true
        },
        "period_end": {
          "name": "period_end",
          "type": "date",
          "primaryKey": false,
          "notNull": true
        },
        "created_at": {
          "name": "created_at",
          "type": "timestamp with time zone",
          "primaryKey": false,
          "notNull": true,
          "default": "now()"
        },
        "due_date": {
          "name": "due_date",
          "type": "timestamp with time zone",
          "primaryKey": false,
          "notNull": true
        }
      },
      "indexes": {},
      "foreignKeys": {
        "invoices_user_id_users_id_fk": {
          "name": "invoices_user_id_users_id_fk",
          "tableFrom": "invoices",
          "tableTo": "users",
          "columnsFrom": [
            "user_id"
          ],
          "columnsTo": [
            "id"
          ],
          "onDelete": "restrict",
          "onUpdate": "no action"
        },
        "invoices_service_point_id_service_points_id_fk": {
          "name": "invoices_service_point_id_service_points_id_fk",
          "tableFrom": "invoices",
          "tableTo": "service_points",
          "columnsFrom": [
            "service_point_id"
          ],
          "columnsTo": [
            "id"
          ],
          "onDelete": "restrict",
          "onUpdate": "no action"
        }
      },
      "compositePrimaryKeys": {},
      "uniqueConstraints": {},
      "policies": {},
      "checkConstraints": {
        "is_due": {
          "name": "is_due",
          "value": "\"invoices\".\"period_end\" > \"invoices\".\"period_start\""
        }
      },
      "isRLSEnabled": false
    },
    "public.meters": {
      "name": "meters",
      "schema": "",
      "columns": {
        "id": {
          "name": "id",
          "type": "uuid",
          "primaryKey": true,
          "notNull": true,
          "default": "gen_random_uuid()"
        },
        "service_point_id": {
          "name": "service_point_id",
          "type": "uuid",
          "primaryKey": false,
          "notNull": true
        },
        "serial_number": {
          "name": "serial_number",
          "type": "varchar(100)",
          "primaryKey": false,
          "notNull": true
        },
        "manufacturer": {
          "name": "manufacturer",
          "type": "varchar(100)",
          "primaryKey": false,
          "notNull": false
        },
        "model": {
          "name": "model",
          "type": "varchar(100)",
          "primaryKey": false,
          "notNull": false
        },
        "firmware_version": {
          "name": "firmware_version",
          "type": "varchar(50)",
          "primaryKey": false,
          "notNull": false
        },
        "meter_status": {
          "name": "meter_status",
          "type": "meter_status",
          "typeSchema": "public",
          "primaryKey": false,
          "notNull": true,
          "default": "'active'"
        },
        "created_at": {
          "name": "created_at",
          "type": "timestamp with time zone",
          "primaryKey": false,
          "notNull": true,
          "default": "now()"
        },
        "last_seen_at": {
          "name": "last_seen_at",
          "type": "timestamp with time zone",
          "primaryKey": false,
          "notNull": false
        }
      },
      "indexes": {},
      "foreignKeys": {
        "meters_service_point_id_service_points_id_fk": {
          "name": "meters_service_point_id_service_points_id_fk",
          "tableFrom": "meters",
          "tableTo": "service_points",
          "columnsFrom": [
            "service_point_id"
          ],
          "columnsTo": [
            "id"
          ],
          "onDelete": "restrict",
          "onUpdate": "no action"
        }
      },
      "compositePrimaryKeys": {},
      "uniqueConstraints": {
        "meters_serial_number_unique": {
          "name": "meters_serial_number_unique",
          "nullsNotDistinct": false,
          "columns": [
            "serial_number"
          ]
        }
      },
      "policies": {},
      "checkConstraints": {},
      "isRLSEnabled": false
    },
    "public.payments": {
      "name": "payments",
      "schema": "",
      "columns": {
        "id": {
          "name": "id",
          "type": "uuid",
          "primaryKey": true,
          "notNull": true,
          "default": "gen_random_uuid()"
        },
        "invoice_id": {
          "name": "invoice_id",
          "type": "uuid",
          "primaryKey": false,
          "notNull": true
        },
        "amount": {
          "name": "amount",
          "type": "numeric(12, 2)",
          "primaryKey": false,
          "notNull": true
        },
        "method": {
          "name": "method",
          "type": "method",
          "typeSchema": "public",
          "primaryKey": false,
          "notNull": true
        },
        "transaction_ref": {
          "name": "transaction_ref",
          "type": "varchar(200)",
          "primaryKey": false,
          "notNull": false
        },
        "payment_status": {
          "name": "payment_status",
          "type": "payment_status",
          "typeSchema": "public",
          "primaryKey": false,
          "notNull": true,
          "default": "'pending'"
        },
        "created_at": {
          "name": "created_at",
          "type": "timestamp with time zone",
          "primaryKey": false,
          "notNull": true,
          "default": "now()"
        }
      },
      "indexes": {},
      "foreignKeys": {
        "payments_invoice_id_invoices_id_fk": {
          "name": "payments_invoice_id_invoices_id_fk",
          "tableFrom": "payments",
          "tableTo": "invoices",
          "columnsFrom": [
            "invoice_id"
          ],
          "columnsTo": [
            "id"
          ],
          "onDelete": "restrict",
          "onUpdate": "no action"
        }
      },
      "compositePrimaryKeys": {},
      "uniqueConstraints": {},
      "policies": {},
      "checkConstraints": {},
      "isRLSEnabled": false
    },
    "public.readings": {
      "name": "readings",
      "schema": "",
      "columns": {
        "id": {
          "name": "id",
          "type": "uuid",
          "primaryKey": true,
          "notNull": true,
          "default": "gen_random_uuid()"
        },
        "meter_id": {
          "name": "meter_id",
          "type": "uuid",
          "primaryKey": false,
          "notNull": true
        },
        "value_kwh": {
          "name": "value_kwh",
          "type": "numeric(12, 4)",
          "primaryKey": false,
          "notNull": true
        },
        "reading_type": {
          "name": "reading_type",
          "type": "reading_type",
          "typeSchema": "public",
          "primaryKey": false,
          "notNull": true,
          "default": "'automatic'"
        },
        "source": {
          "name": "source",
          "type": "varchar(50)",
          "primaryKey": false,
          "notNull": false
        },
        "created_at": {
          "name": "created_at",
          "type": "timestamp with time zone",
          "primaryKey": false,
          "notNull": true,
          "default": "now()"
        }
      },
      "indexes": {
        "idx_readings_meter_time": {
          "name": "idx_readings_meter_time",
          "columns": [
            {
              "expression": "meter_id",
              "isExpression": false,
              "asc": true,
              "nulls": "last"
            },
            {
              "expression": "created_at",
              "isExpression": false,
              "asc": false,
              "nulls": "last"
            }
          ],
          "isUnique": false,
          "concurrently": false,
          "method": "btree",
          "with": {}
        }
      },
      "foreignKeys": {
        "readings_meter_id_meters_id_fk": {
          "name": "readings_meter_id_meters_id_fk",
          "tableFrom": "readings",
          "tableTo": "meters",
          "columnsFrom": [
            "meter_id"
          ],
          "columnsTo": [
            "id"
          ],
          "onDelete": "cascade",
          "onUpdate": "no action"
        }
      },
      "compositePrimaryKeys": {},
      "uniqueConstraints": {},
      "policies": {},
      "checkConstraints": {},
      "isRLSEnabled": false
    },
    "public.service_points": {
      "name": "service_points",
      "schema": "",
      "columns": {
        "id": {
          "name": "id",
          "type": "uuid",
          "primaryKey": true,
          "notNull": true,
          "default": "gen_random_uuid()"
        },
        "user_id": {
          "name": "user_id",
          "type": "uuid",
          "primaryKey": false,
          "notNull": true
        },
        "tarrif_id": {
          "name": "tarrif_id",
          "type": "uuid",
          "primaryKey": false,
          "notNull": false
        },
        "address": {
          "name": "address",
          "type": "text",
          "primaryKey": false,
          "notNull": true
        },
        "coordinates": {
          "name": "coordinates",
          "type": "point",
          "primaryKey": false,
          "notNull": false
        },
        "connection_type": {
          "name": "connection_type",
          "type": "connection_type",
          "typeSchema": "public",
          "primaryKey": false,
          "notNull": true,
          "default": "'residential'"
        },
        "activated_at": {
          "name": "activated_at",
          "type": "timestamp with time zone",
          "primaryKey": false,
          "notNull": false
        }
      },
      "indexes": {},
      "foreignKeys": {
        "service_points_user_id_users_id_fk": {
          "name": "service_points_user_id_users_id_fk",
          "tableFrom": "service_points",
          "tableTo": "users",
          "columnsFrom": [
            "user_id"
          ],
          "columnsTo": [
            "id"
          ],
          "onDelete": "restrict",
          "onUpdate": "no action"
        },
        "service_points_tarrif_id_tariffs_id_fk": {
          "name": "service_points_tarrif_id_tariffs_id_fk",
          "tableFrom": "service_points",
          "tableTo": "tariffs",
          "columnsFrom": [
            "tarrif_id"
          ],
          "columnsTo": [
            "id"
          ],
          "onDelete": "no action",
          "onUpdate": "no action"
        }
      },
      "compositePrimaryKeys": {},
      "uniqueConstraints": {},
      "policies": {},
      "checkConstraints": {},
      "isRLSEnabled": false
    },
    "public.tariffs": {
      "name": "tariffs",
      "schema": "",
      "columns": {
        "id": {
          "name": "id",
          "type": "uuid",
          "primaryKey": true,
          "notNull": true,
          "default": "gen_random_uuid()"
        },
        "name": {
          "name": "name",
          "type": "varchar(100)",
          "primaryKey": false,
          "notNull": true
        },
        "type": {
          "name": "type",
          "type": "type",
          "typeSchema": "public",
          "primaryKey": false,
          "notNull": true
        },
        "base_rate": {
          "name": "base_rate",
          "type": "numeric(10, 6)",
          "primaryKey": false,
          "notNull": true
        },
        "peak_rate": {
          "name": "peak_rate",
          "type": "numeric(10, 6)",
          "primaryKey": false,
          "notNull": false
        },
        "off_peak_rate": {
          "name": "off_peak_rate",
          "type": "numeric(10, 6)",
          "primaryKey": false,
          "notNull": false
        },
        "effective_from": {
          "name": "effective_from",
          "type": "timestamp with time zone",
          "primaryKey": false,
          "notNull": true
        },
        "effective_to": {
          "name": "effective_to",
          "type": "timestamp with time zone",
          "primaryKey": false,
          "notNull": false
        }
      },
      "indexes": {},
      "foreignKeys": {},
      "compositePrimaryKeys": {},
      "uniqueConstraints": {},
      "policies": {},
      "checkConstraints": {},
      "isRLSEnabled": false
    },
    "public.users": {
      "name": "users",
      "schema": "",
      "columns": {
        "id": {
          "name": "id",
          "type": "uuid",
          "primaryKey": true,
          "notNull": true,
          "default": "gen_random_uuid()"
        },
        "full_name": {
          "name": "full_name",
          "type": "varchar(150)",
          "primaryKey": false,
          "notNull": true
        },
        "email": {
          "name": "email",
          "type": "varchar(255)",
          "primaryKey": false,
          "notNull": true
        },
        "phone": {
          "name": "phone",
          "type": "varchar(30)",
          "primaryKey": false,
          "notNull": false
        },
        "address": {
          "name": "address",
          "type": "text",
          "primaryKey": false,
          "notNull": false
        },
        "account_status": {
          "name": "account_status",
          "type": "account_status",
          "typeSchema": "public",
          "primaryKey": false,
          "notNull": true,
          "default": "'active'"
        },
        "created_at": {
          "name": "created_at",
          "type": "timestamp with time zone",
          "primaryKey": false,
          "notNull": true,
          "default": "now()"
        }
      },
      "indexes": {},
      "foreignKeys": {},
      "compositePrimaryKeys": {},
      "uniqueConstraints": {
        "users_email_unique": {
          "name": "users_email_unique",
          "nullsNotDistinct": false,
          "columns": [
            "email"
          ]
        }
      },
      "policies": {},
      "checkConstraints": {},
      "isRLSEnabled": false
    }
  },
  "enums": {
    "public.account_status": {
      "name": "account_status",
      "schema": "public",
      "values": [
        "active",
        "suspended",
        "closed"
      ]
    },
    "public.alert_type": {
      "name": "alert_type",
      "schema": "public",
      "values": [
        "tamper",
        "outage",
        "high_usage",
        "low_battery"
      ]
    },
    "public.connection_type": {
      "name": "connection_type",
      "schema": "public",
      "values": [
        "residential",
        "commercial",
        "industrial"
      ]
    },
    "public.invoice_status": {
      "name": "invoice_status",
      "schema": "public",
      "values": [
        "unpaid",
        "paid",
        "overdue",
        "disputed",
        "cancelled"
      ]
    },
    "public.meter_status": {
      "name": "meter_status",
      "schema": "public",
      "values": [
        "active",
        "inactive",
        "faulty",
        "decommissioned"
      ]
    },
    "public.method": {
      "name": "method",
      "schema": "public",
      "values": [
        "bank_transfer",
        "card",
        "ussd",
        "cash",
        "wallet"
      ]
    },
    "public.payment_status": {
      "name": "payment_status",
      "schema": "public",
      "values": [
        "pending",
        "successful",
        "failed",
        "reversed"
      ]
    },
    "public.reading_type": {
      "name": "reading_type",
      "schema": "public",
      "values": [
        "automatic",
        "manual",
        "estimated"
      ]
    },
    "public.severity": {
      "name": "severity",
      "schema": "public",
      "values": [
        "info",
        "warning",
        "critical"
      ]
    },
    "public.type": {
      "name": "type",
      "schema": "public",
      "values": [
        "flat",
        "time_of_use",
        "tiered"
      ]
    }
  },
  "schemas": {},
  "sequences": {},
  "roles": {},
  "policies": {},
  "views": {},
  "_meta": {
    "columns": {},
    "schemas": {},
    "tables": {}
  }
}